auto_duo
