Metadata-Version: 2.1
Name: auto-duo
Version: 1.0.0
Summary: Autotamically pass each duo push, no need to click on cellphone.
Home-page: https://github.com/jtc1246/auto-duo
Author: Tiancheng Jiao
Author-email: jtc1246@outlook.com
License: GPL-2.0 License
Platform: all
Requires-Python: >=3.9
License-File: LICENSE
